Metadata-Version: 2.1
Name: hakkero-dataloader
Version: 1.2.23
Home-page: https://github.com/ericxsun/hakkero-dataloader
Keywords: Pytorch LM dataloader
Requires-Dist: numpy
Requires-Dist: torch
Requires-Dist: h5py
Requires-Dist: bitarray>=2.9.2
Requires-Dist: tabulate
Requires-Dist: scipy
Requires-Dist: msgspec
Requires-Dist: msgpack>=0.5.2
Requires-Dist: Pillow
